skillbridge/__init__.py
skillbridge/__main__.py
skillbridge/py.typed
skillbridge/version.py
skillbridge/client/__init__.py
skillbridge/client/channel.py
skillbridge/client/functions.py
skillbridge/client/globals.py
skillbridge/client/hints.py
skillbridge/client/objects.py
skillbridge/client/remote.py
skillbridge/client/translator.py
skillbridge/client/var.py
skillbridge/client/workspace.py
skillbridge/server/__init__.py
skillbridge/server/python_server.il
skillbridge/server/python_server.py
skillbridge/test/__init__.py
skillbridge/test/channel.py
skillbridge/test/translator.py
skillbridge/test/workspace.py
skillbridge-1.7.3.dist-info/LICENSE
skillbridge-1.7.3.dist-info/METADATA
skillbridge-1.7.3.dist-info/WHEEL
skillbridge-1.7.3.dist-info/entry_points.txt
skillbridge-1.7.3.dist-info/top_level.txt
skillbridge-1.7.3.dist-info/RECORD
