Metadata-Version: 2.2
Name: skillbridge
Version: 1.7.3
Summary: A seamless Python remote bridge to Cadence's Skill in Virtuoso
Author-email: Niels Buwen <dev@niels-buwen.de>, Tobias Markus <tobias_markus@gmx.net>
License:                    GNU LESSER GENERAL PUBLIC LICENSE
Project-URL: Repository, https://github.com/unihd-cag/skillbridge
Classifier: Development Status :: 5 - Production/Stable
Classifier: Programming Language :: Python :: 3
Classifier: Programming Language :: Python :: 3.8
Classifier: Programming Language :: Python :: 3.9
Classifier: Programming Language :: Python :: 3.10
Classifier: Programming Language :: Python :: 3.11
Classifier: Intended Audience :: Developers
Classifier: Intended Audience :: Science/Research
Classifier: Intended Audience :: Information Technology
Classifier: Operating System :: POSIX :: Linux
Classifier: Topic :: Scientific/Engineering :: Electronic Design Automation (EDA)
Classifier: Topic :: Software Development
Classifier: License :: OSI Approved :: GNU Lesser General Public License v3 (LGPLv3)
Requires-Python: >=3.8
License-File: LICENSE
Provides-Extra: dev
Requires-Dist: pytest; extra == "dev"
Requires-Dist: pytest-coverage; extra == "dev"
Requires-Dist: hypothesis; extra == "dev"
Requires-Dist: mypy; extra == "dev"
Requires-Dist: ruff>=0.2.1; extra == "dev"
Provides-Extra: doc
Requires-Dist: sphinx; extra == "doc"
